tsxml/__init__.py
tsxml/main.py
tsxml/types/array.py
tsxml/types/boolean.py
tsxml/types/container.py
tsxml/types/number.py
tsxml/types/string.py
tsxml-0.1.0.dist-info/LICENSE
tsxml-0.1.0.dist-info/METADATA
tsxml-0.1.0.dist-info/WHEEL
tsxml-0.1.0.dist-info/RECORD
